git_cli_tool/__init__.py
git_cli_tool/git_cli_tool.py
git_cli_tool-1.0.0.dist-info/licenses/LICENSE
git_cli_tool-1.0.0.dist-info/METADATA
git_cli_tool-1.0.0.dist-info/WHEEL
git_cli_tool-1.0.0.dist-info/entry_points.txt
git_cli_tool-1.0.0.dist-info/top_level.txt
git_cli_tool-1.0.0.dist-info/RECORD
