Metadata-Version: 2.4
Name: git-cli-tool
Version: 1.0.0
Summary: A professional Git CLI wrapper with enhanced user experience
Author-email: َAmirHoseinBlue <amirakhlagh893@gmail.com>
Maintainer-email: َAmirHoseinBlue <amirakhlagh893@gmail.com>
License: MIT
Project-URL: Homepage, https://github.com/َAmirHoseinBlue24/git-cli-tool
Project-URL: Bug Reports, https://github.com/َAmirHoseinBlue24/git-cli-tool/issues
Project-URL: Source, https://github.com/َAmirHoseinBlue24/git-cli-tool
Keywords: git,cli,tool,wrapper,version-control
Classifier: Development Status :: 5 - Production/Stable
Classifier: Intended Audience :: Developers
Classifier: Topic :: Software Development :: Version Control :: Git
Classifier: Programming Language :: Python :: 3
Classifier: Programming Language :: Python :: 3.7
Classifier: Programming Language :: Python :: 3.8
Classifier: Programming Language :: Python :: 3.9
Classifier: Programming Language :: Python :: 3.10
Classifier: Programming Language :: Python :: 3.11
Classifier: Programming Language :: Python :: 3.12
Classifier: Programming Language :: Python :: 3.13
Classifier: Operating System :: OS Independent
Requires-Python: >=3.7
License-File: LICENSE
Dynamic: license-file
